reed/__init__.py
reed/__main__.py
reed/content.py
reed/web.py
reeder-0.1.0.dist-info/licenses/LICENSE
reeder-0.1.0.dist-info/METADATA
reeder-0.1.0.dist-info/WHEEL
reeder-0.1.0.dist-info/entry_points.txt
reeder-0.1.0.dist-info/top_level.txt
reeder-0.1.0.dist-info/RECORD
