Metadata-Version: 2.4
Name: reeder
Version: 0.1.0
Summary: Textify a resource
Requires-Python: >=3.10
License-File: LICENSE
Requires-Dist: beautifulsoup4>=4.13.4
Requires-Dist: click>=8.1.8
Requires-Dist: deal>=4.24.5
Requires-Dist: httpx>=0.28.1
Requires-Dist: pdfminer-six[image]>=20250416
Requires-Dist: python-readability>=0.1.3
Requires-Dist: yt-dlp>=2025.3.31
Dynamic: license-file
